dependencyfixer/__init__.py
dependencyfixer/dependencyfixer.py
dependency_fixer-1.0.2.dist-info/LICENSE
dependency_fixer-1.0.2.dist-info/METADATA
dependency_fixer-1.0.2.dist-info/WHEEL
dependency_fixer-1.0.2.dist-info/top_level.txt
dependency_fixer-1.0.2.dist-info/RECORD
