Metadata-Version: 2.1
Name: dependency-fixer
Version: 1.0.2
Summary: A simple inscript multi-package installer
Home-page: https://github.com/avinashkarhana/dependencyfixer
Author: Avinash Karhana
Author-email: avinashkarhana1@gmail.com
License: UNKNOWN
Keywords: dependencyfixer,dependencyhandler,dependency-fixer
Platform: UNKNOWN
Classifier: Programming Language :: Python :: 3
Classifier: Programming Language :: Python :: 3.6
Classifier: Programming Language :: Python :: 3.7
Classifier: Programming Language :: Python :: 3.8
Classifier: License :: OSI Approved :: MIT License
Classifier: Operating System :: OS Independent
Requires-Python: >=3.5
Requires-Dist: pip (>=20.0)
